sqbased/__main__.py
sqbased-0.1.2.dist-info/METADATA
sqbased-0.1.2.dist-info/WHEEL
sqbased-0.1.2.dist-info/entry_points.txt
sqbased-0.1.2.dist-info/RECORD
