Metadata-Version: 2.1
Name: sqbased
Version: 0.1.2
Summary: 
Author: redthing1
Author-email: redthing1@alt.icu
Requires-Python: >=3.9,<4.0
Classifier: Programming Language :: Python :: 3
Classifier: Programming Language :: Python :: 3.9
Classifier: Programming Language :: Python :: 3.10
Classifier: Programming Language :: Python :: 3.11
Requires-Dist: humanfriendly (>=10.0,<11.0)
Requires-Dist: minlog (>=0.1.0,<0.2.0)
Requires-Dist: sh (>=2.0.4,<3.0.0)
Requires-Dist: typer (>=0.9.0,<0.10.0)
